{"box_data": [{"position": {"minX": 295.25, "minY": 151.75, "maxX": 493.25, "maxY": 313.5}, "class_id": 1, "box_caption": "Potato 0.901", "scores": {"class_score": 0.90087890625}, "domain": "pixel"}, {"position": {"minX": 161.25, "minY": 139.5, "maxX": 303.5, "maxY": 267.5}, "class_id": 1, "box_caption": "Potato 0.887", "scores": {"class_score": 0.88720703125}, "domain": "pixel"}, {"position": {"minX": 259.25, "minY": 88.875, "maxX": 409.25, "maxY": 196.125}, "class_id": 1, "box_caption": "Potato 0.886", "scores": {"class_score": 0.88623046875}, "domain": "pixel"}, {"position": {"minX": 164.125, "minY": 141.0, "maxX": 304.5, "maxY": 264.25}, "class_id": 0, "box_caption": "Apple 0.014", "scores": {"class_score": 0.013580322265625}, "domain": "pixel"}, {"position": {"minX": 258.25, "minY": 89.375, "maxX": 408.75, "maxY": 192.875}, "class_id": 0, "box_caption": "Apple 0.011", "scores": {"class_score": 0.01092529296875}, "domain": "pixel"}, {"position": {"minX": 267.5, "minY": 104.9375, "maxX": 437.5, "maxY": 229.5}, "class_id": 1, "box_caption": "Potato 0.006", "scores": {"class_score": 0.006084442138671875}, "domain": "pixel"}, {"position": {"minX": 332.0, "minY": 157.0, "maxX": 450.5, "maxY": 306.25}, "class_id": 1, "box_caption": "Potato 0.005", "scores": {"class_score": 0.005260467529296875}, "domain": "pixel"}, {"position": {"minX": 295.0, "minY": 152.625, "maxX": 493.0, "maxY": 313.0}, "class_id": 0, "box_caption": "Apple 0.005", "scores": {"class_score": 0.005252838134765625}, "domain": "pixel"}, {"position": {"minX": 284.0, "minY": 105.0, "maxX": 396.5, "maxY": 207.25}, "class_id": 1, "box_caption": "Potato 0.002", "scores": {"class_score": 0.00229644775390625}, "domain": "pixel"}, {"position": {"minX": 648.0, "minY": 309.75, "maxX": 668.0, "maxY": 399.25}, "class_id": 0, "box_caption": "Apple 0.002", "scores": {"class_score": 0.0022296905517578125}, "domain": "pixel"}, {"position": {"minX": 179.75, "minY": 164.75, "maxX": 301.25, "maxY": 254.5}, "class_id": 1, "box_caption": "Potato 0.001", "scores": {"class_score": 0.0014753341674804688}, "domain": "pixel"}, {"position": {"minX": 656.5, "minY": 302.0, "maxX": 673.5, "maxY": 404.5}, "class_id": 0, "box_caption": "Apple 0.001", "scores": {"class_score": 0.0012388229370117188}, "domain": "pixel"}, {"position": {"minX": 306.0, "minY": 141.0, "maxX": 479.0, "maxY": 244.0}, "class_id": 1, "box_caption": "Potato 0.001", "scores": {"class_score": 0.0011148452758789062}, "domain": "pixel"}], "class_labels": {"0": "Apple", "1": "Potato"}}