{"box_data": [{"position": {"minX": 33.125, "minY": 94.25, "maxX": 502.5, "maxY": 650.0}, "class_id": 0, "box_caption": "apple 0.632", "scores": {"class_score": 0.63232421875}, "domain": "pixel"}, {"position": {"minX": 25.0, "minY": 14.75, "maxX": 675.0, "maxY": 552.0}, "class_id": 0, "box_caption": "apple 0.025", "scores": {"class_score": 0.0250091552734375}, "domain": "pixel"}, {"position": {"minX": 32.875, "minY": 79.0, "maxX": 475.0, "maxY": 660.0}, "class_id": 1, "box_caption": "banana 0.019", "scores": {"class_score": 0.019378662109375}, "domain": "pixel"}, {"position": {"minX": 376.75, "minY": 232.625, "maxX": 596.0, "maxY": 616.5}, "class_id": 0, "box_caption": "apple 0.013", "scores": {"class_score": 0.01253509521484375}, "domain": "pixel"}, {"position": {"minX": 81.5, "minY": -34.125, "maxX": 646.5, "maxY": 392.0}, "class_id": 0, "box_caption": "apple 0.008", "scores": {"class_score": 0.0082550048828125}, "domain": "pixel"}, {"position": {"minX": 48.5, "minY": -10.0, "maxX": 681.5, "maxY": 315.0}, "class_id": 1, "box_caption": "banana 0.008", "scores": {"class_score": 0.00800323486328125}, "domain": "pixel"}, {"position": {"minX": 261.5, "minY": 117.0, "maxX": 636.5, "maxY": 638.5}, "class_id": 0, "box_caption": "apple 0.008", "scores": {"class_score": 0.0079803466796875}, "domain": "pixel"}, {"position": {"minX": 69.125, "minY": 220.75, "maxX": 466.5, "maxY": 569.0}, "class_id": 0, "box_caption": "apple 0.007", "scores": {"class_score": 0.00714111328125}, "domain": "pixel"}, {"position": {"minX": -9.25, "minY": -55.375, "maxX": 671.0, "maxY": 477.0}, "class_id": 1, "box_caption": "banana 0.004", "scores": {"class_score": 0.00444793701171875}, "domain": "pixel"}, {"position": {"minX": 44.125, "minY": 165.375, "maxX": 250.875, "maxY": 587.0}, "class_id": 0, "box_caption": "apple 0.002", "scores": {"class_score": 0.0024433135986328125}, "domain": "pixel"}, {"position": {"minX": 458.75, "minY": 203.625, "maxX": 628.5, "maxY": 616.5}, "class_id": 0, "box_caption": "apple 0.002", "scores": {"class_score": 0.0024127960205078125}, "domain": "pixel"}, {"position": {"minX": -6.109375, "minY": 99.25, "maxX": 48.1875, "maxY": 630.0}, "class_id": 1, "box_caption": "banana 0.002", "scores": {"class_score": 0.00231170654296875}, "domain": "pixel"}, {"position": {"minX": 88.0, "minY": 2.125, "maxX": 653.5, "maxY": 193.5}, "class_id": 1, "box_caption": "banana 0.002", "scores": {"class_score": 0.001987457275390625}, "domain": "pixel"}, {"position": {"minX": 32.875, "minY": 79.0, "maxX": 475.0, "maxY": 660.0}, "class_id": 2, "box_caption": "carrot 0.002", "scores": {"class_score": 0.0016632080078125}, "domain": "pixel"}, {"position": {"minX": 327.0, "minY": 210.625, "maxX": 548.5, "maxY": 608.0}, "class_id": 0, "box_caption": "apple 0.001", "scores": {"class_score": 0.0011310577392578125}, "domain": "pixel"}, {"position": {"minX": 619.5, "minY": 161.375, "maxX": 680.5, "maxY": 626.0}, "class_id": 0, "box_caption": "apple 0.001", "scores": {"class_score": 0.0011186599731445312}, "domain": "pixel"}], "class_labels": {"0": "apple", "1": "banana", "2": "carrot"}}